setup.cfg
setup.py
pybip38/__init__.py
pybip38/bip38.py
pybip38.egg-info/PKG-INFO
pybip38.egg-info/SOURCES.txt
pybip38.egg-info/dependency_links.txt
pybip38.egg-info/requires.txt
pybip38.egg-info/top_level.txt